[
  {
    "question": "How to reduce the ecological footprint?",
    "answer": "Reducing waste"
  },
  {
    "question": "In what year was the Chanel brand founded?",
    "answer": "1910"
  },
  {
    "question": "In what year was the first fashion show held?",
    "answer": "1903"
  },
  {
    "question": "In which country is the Boa Vista Fashion Week held?",
    "answer": "Cape Verde"
  },
  {
    "question": "What accessories were worn during the Renaissance era?",
    "answer": "Pearls"
  },
  {
    "question": "What accessory is often used to clip a tie?",
    "answer": "Tie clip"
  },
  {
    "question": "What are high fashion models called?",
    "answer": "Haute couture"
  },
  {
    "question": "What characteristics are associated with haute couture?",
    "answer": "Uniqueness"
  },
  {
    "question": "What clothing is most commonly chosen for sports activities in 2023?",
    "answer": "Leggings"
  },
  {
    "question": "What clothing item is traditionally paired with a pencil skirt?",
    "answer": "Blouse"
  },
  {
    "question": "What does 'патентная кожа' mean?",
    "answer": "Patent leather"
  },
  {
    "question": "What dresses were in fashion during the Victorian era?",
    "answer": "Corsets and crinolines"
  },
  {
    "question": "What event annually attracts many celebrities?",
    "answer": "Met Gala"
  },
  {
    "question": "What helps reduce the carbon footprint in fashion?",
    "answer": "Recycling fabrics"
  },
  {
    "question": "What indicates that a suit belongs to the sports style?",
    "answer": "Sport stripes"
  },
  {
    "question": "What is the hairstyle of the 1920s called?",
    "answer": "Bob"
  },
  {
    "question": "What is the name of men's shoes with a pointed toe?",
    "answer": "Oxfords"
  },
  {
    "question": "What is the name of the creative director of Balenciaga?",
    "answer": "Demna Gvasalia"
  },
  {
    "question": "What is the name of the fashion week on Sixth Avenue in New York?",
    "answer": "Made Fashion Week"
  },
  {
    "question": "What is the name of the mesh fabric used for sportswear?",
    "answer": "Mesh"
  },
  {
    "question": "What is the process of creating clothing using sensors called?",
    "answer": "Smart fabrics"
  },
  {
    "question": "What popular pattern is used in jewelry?",
    "answer": "Fleur-de-lis"
  },
  {
    "question": "What shoes automatically tighten on the foot?",
    "answer": "Nike Adapt"
  },
  {
    "question": "What style of clothing is most often chosen for school?",
    "answer": "Classic"
  },
  {
    "question": "What style was popular in the early 19th century?",
    "answer": "Classicism"
  },
  {
    "question": "What technology is used in smart sneakers?",
    "answer": "Piezo sensors"
  },
  {
    "question": "What trend contributes to more conscious consumption in fashion?",
    "answer": "Conscious consumption"
  },
  {
    "question": "What type of boots are often worn in the summer?",
    "answer": "Mesh boots"
  },
  {
    "question": "What type of footwear can change size?",
    "answer": "Adaptive sneakers"
  },
  {
    "question": "What type of footwear is associated with luxury leisure?",
    "answer": "Loafers"
  },
  {
    "question": "When did Ralph Lauren start his career?",
    "answer": "1967"
  },
  {
    "question": "Which French designer became famous for his avant-garde collections?",
    "answer": "Jean-Paul Gaultier"
  },
  {
    "question": "Which Japanese brand is known for innovative streetwear?",
    "answer": "A Bathing Ape"
  },
  {
    "question": "Which Prada collection became a symbol of minimalism?",
    "answer": "Minimal Baroque"
  },
  {
    "question": "Which brand created the concert costumes for Beyoncé's 'Formation' tour?",
    "answer": "Balmain"
  },
  {
    "question": "Which brand is famous for its fedoras?",
    "answer": "Borsalino"
  },
  {
    "question": "Which brand is famous for its footwear?",
    "answer": "Cole Haan"
  },
  {
    "question": "Which brand is famous for its linen suits?",
    "answer": "Ermenegildo Zegna"
  },
  {
    "question": "Which brand is famous for producing suitcases and bags?",
    "answer": "Louis Vuitton"
  },
  {
    "question": "Which brand is known for its minimalist design solutions?",
    "answer": "Celine"
  },
  {
    "question": "Which brand is known for its unusual hats?",
    "answer": "Philip Treacy"
  },
  {
    "question": "Which brand is renowned for its elegant and stylish evening gowns?",
    "answer": "Oscar de la Renta"
  },
  {
    "question": "Which brand often collaborates with artists to create unique collections?",
    "answer": "Louis Vuitton"
  },
  {
    "question": "Which brand produces clothing in the working-class style?",
    "answer": "Carhartt"
  },
  {
    "question": "Which company uses mushrooms to create materials?",
    "answer": "MycoWorks"
  },
  {
    "question": "Which designer created the iconic dresses for Jacqueline Kennedy?",
    "answer": "Oleg Cassini"
  },
  {
    "question": "Which designer is known for collaborations with famous musicians?",
    "answer": "Rick Owens"
  },
  {
    "question": "Which designer is known for their red carpet dresses?",
    "answer": "Elie Saab"
  },
  {
    "question": "Which designer was the first to introduce the concept of unisex in their collections?",
    "answer": "Jean-Paul Gaultier"
  },
  {
    "question": "Which fabric was popular in the 1990s?",
    "answer": "Pleats"
  },
  {
    "question": "Which fashion brand released a collection of bags with balloons?",
    "answer": "Anya Hindmarch"
  },
  {
    "question": "Which fashion brand was founded by Pierre Balmain?",
    "answer": "Balmain"
  },
  {
    "question": "Which fashion company is eco-friendly?",
    "answer": "Patagonia"
  },
  {
    "question": "Which fashion designer introduced asymmetrical hemlines?",
    "answer": "Thierry Mugler"
  },
  {
    "question": "Which fashion designer was the first to introduce the concept of 'ready-to-wear'?",
    "answer": "Pierre Cardin"
  },
  {
    "question": "Which fashion house used augmented reality in their 2018 show?",
    "answer": "Burberry"
  },
  {
    "question": "Which street fashion item is popular among artists?",
    "answer": "Beret"
  },
  {
    "question": "Which style came back into fashion in spring 2023?",
    "answer": "Retro"
  },
  {
    "question": "Which style includes the cinema style?",
    "answer": "Glamour"
  },
  {
    "question": "Which technology reduces waste?",
    "answer": "3D printing"
  },
  {
    "question": "Who annually chairs the organizing committee of the Met Gala?",
    "answer": "Anna Wintour"
  },
  {
    "question": "Who first popularized the bomber jacket?",
    "answer": "U.S. Air Force"
  },
  {
    "question": "Who introduced the fashion for lace in the Victorian era?",
    "answer": "Queen Victoria"
  },
  {
    "question": "Who is referred to as the 'icon of high fashion'?",
    "answer": "Karl Lagerfeld"
  },
  {
    "question": "Who is the creative director of Dior?",
    "answer": "Maria Grazia Chiuri"
  },
  {
    "question": "Who is the designer of the brand 'JW Anderson'?",
    "answer": "Jonathan Anderson"
  },
  {
    "question": "Who led the fashion house Balenciaga before Demna Gvasalia?",
    "answer": "Alexander Wang"
  },
  {
    "question": "Who was the artistic director of Dior in 1989?",
    "answer": "Gianfranco Ferré"
  },
  {
    "question": "Who was the designer of Björk's famous swan dress?",
    "answer": "Marjan Pejoski"
  }
]
