[
  {
    "question": "For which board game are twenty tokens required?",
    "answer": "Trivial Pursuit"
  },
  {
    "question": "For which game do you need to build a castle of legions?",
    "answer": "Fortress"
  },
  {
    "question": "How many games are there in the main Resident Evil series?",
    "answer": "8"
  },
  {
    "question": "How many hours per week does a top football streamer stream?",
    "answer": "20 hours"
  },
  {
    "question": "How many levels are there in Candy Crush Saga?",
    "answer": "10000+ levels"
  },
  {
    "question": "How many levels are there in the game Monument Valley 2?",
    "answer": "Fourteen"
  },
  {
    "question": "How many phases are there in the game 'Pandemic'?",
    "answer": "5"
  },
  {
    "question": "How many segments are in a snake?",
    "answer": "13"
  },
  {
    "question": "How often are playlists on music streaming services updated?",
    "answer": "Weekly"
  },
  {
    "question": "How often are podcasts released?",
    "answer": "Weekly"
  },
  {
    "question": "In what setting does the game Metro Exodus take place?",
    "answer": "Post-apocalypse"
  },
  {
    "question": "In what year did the channel 'Lunch without Problems' appear?",
    "answer": "2012"
  },
  {
    "question": "In what year was Hearthstone released?",
    "answer": "2014"
  },
  {
    "question": "In what year was the first DreamHack tournament held?",
    "answer": "1994"
  },
  {
    "question": "In what year was the first game of the Final Fantasy series released?",
    "answer": "1987"
  },
  {
    "question": "In what year was the game 'Monopoly' released?",
    "answer": "1935"
  },
  {
    "question": "In what year was the game Watch Dogs: Legion released?",
    "answer": "2020"
  },
  {
    "question": "In what year was the original Warcraft game released?",
    "answer": "1994"
  },
  {
    "question": "In what year was the original version of the game Doom released?",
    "answer": "1993"
  },
  {
    "question": "In which 1997 game do claymation characters appear?",
    "answer": "The Neverhood"
  },
  {
    "question": "In which VR game can players create their own levels?",
    "answer": "Dreams"
  },
  {
    "question": "In which VR game can you control gravity and physics?",
    "answer": "Boneworks"
  },
  {
    "question": "In which VR game do you fight against zombies in an animated style?",
    "answer": "Arizona Sunshine"
  },
  {
    "question": "In which board game do players explore and fight for treasures on the lost island of Arnak?",
    "answer": "Lost Ruins of Arnak"
  },
  {
    "question": "In which board game do players try to build the most powerful civilization?",
    "answer": "Through the Ages"
  },
  {
    "question": "In which city was the DreamHack Winter 2013 tournament held?",
    "answer": "Jönköping"
  },
  {
    "question": "In which country was the Six Invitational 2020 tournament held?",
    "answer": "Canada"
  },
  {
    "question": "In which game are the characters pilots of mechanical robots?",
    "answer": "Titanfall"
  },
  {
    "question": "In which game are the main characters pilots of mechanical robots?",
    "answer": "Into the Breach"
  },
  {
    "question": "In which game are there elementals?",
    "answer": "Divinity: Original Sin"
  },
  {
    "question": "In which game are there transportation cards?",
    "answer": "Ticket to Ride"
  },
  {
    "question": "In which game can you become a pilot of a spaceship?",
    "answer": "Elite Dangerous"
  },
  {
    "question": "In which game can you become the captain of a spaceship?",
    "answer": "FTL: Faster Than Light"
  },
  {
    "question": "In which game can you develop a mountain base?",
    "answer": "Frostpunk"
  },
  {
    "question": "In which game can you face alien threats?",
    "answer": "X-COM"
  },
  {
    "question": "In which game can you fly on dragons?",
    "answer": "Dragon Age"
  },
  {
    "question": "In which game do players control a Roman legion?",
    "answer": "Concordia"
  },
  {
    "question": "In which game do players control characters in a dark fantasy world?",
    "answer": "Gloomhaven"
  },
  {
    "question": "In which game do players explore planets and find artifacts while solving puzzles?",
    "answer": "Outer Wilds"
  },
  {
    "question": "In which game do you control a kite?",
    "answer": "Kite Runner"
  },
  {
    "question": "In which game do you drive a bus?",
    "answer": "Bus Simulator"
  },
  {
    "question": "In which game do you explore dungeons and roll dice for battles?",
    "answer": "DungeonQuest"
  },
  {
    "question": "In which game do you manage an amusement park?",
    "answer": "RollerCoaster Tycoon"
  },
  {
    "question": "In which game do you need to build a spaceship to escape?",
    "answer": "Outer Wilds"
  },
  {
    "question": "In which game do you need to develop a post-apocalyptic society and gather resources for survival?",
    "answer": "Frostpunk"
  },
  {
    "question": "In which game do you need to maintain the survival of characters on an alien planet?",
    "answer": "Oxygen Not Included"
  },
  {
    "question": "In which game do you need to use a mask for survival?",
    "answer": "Subnautica"
  },
  {
    "question": "In which game do you save the world by scavenging through trash?",
    "answer": "Fallout"
  },
  {
    "question": "In which game do you solve puzzles in a world of isometric projections?",
    "answer": "Fez"
  },
  {
    "question": "In which game does the Apex Predators cult exist?",
    "answer": "Titanfall 2"
  },
  {
    "question": "In which game does the Brotherhood of Steel faction appear?",
    "answer": "Fallout"
  },
  {
    "question": "In which game does the action take place in Chernobyl?",
    "answer": "S.T.A.L.K.E.R."
  },
  {
    "question": "In which game does the action take place on an abandoned spaceship?",
    "answer": "Dead Space"
  },
  {
    "question": "In which game does the hero face mythical creatures?",
    "answer": "Dark Souls III"
  },
  {
    "question": "In which game is Alduin featured?",
    "answer": "Skyrim"
  },
  {
    "question": "In which game is a D20 die used?",
    "answer": "Dungeons & Dragons"
  },
  {
    "question": "In which game is a post-apocalyptic world explored, ravaged by giant machines?",
    "answer": "Horizon Zero Dawn"
  },
  {
    "question": "In which game is the 'Pip-Boy' used?",
    "answer": "Fallout"
  },
  {
    "question": "In which game is the FaZe Clan team popular?",
    "answer": "Call of Duty"
  },
  {
    "question": "In which game is the Nephalem Stone used?",
    "answer": "Diablo III"
  },
  {
    "question": "In which game is the character Bao-Dur featured?",
    "answer": "Star Wars: KotOR II"
  },
  {
    "question": "In which game is the character Jesse Faden featured?",
    "answer": "Control"
  },
  {
    "question": "In which game is the location Lileynoe Pole featured?",
    "answer": "Xenoblade Chronicles"
  },
  {
    "question": "In which game is the main character Kazuma Kiryu?",
    "answer": "Yakuza"
  },
  {
    "question": "In which game is the main character named Baokai?",
    "answer": "Prey"
  },
  {
    "question": "In which game is the main mechanic based on time manipulation?",
    "answer": "Braid"
  },
  {
    "question": "In which game is the main task to manage a fleet?",
    "answer": "Homeworld"
  },
  {
    "question": "In which game is the story told from the perspective of an android named 2B?",
    "answer": "Nier: Automata"
  },
  {
    "question": "In which game is the synergy of music and visual effects important?",
    "answer": "Crypt of the Necrodancer"
  },
  {
    "question": "In which genre of games is the esports player 'Scarlett' known?",
    "answer": "RTS"
  },
  {
    "question": "In which month did the podcast 'Business Stories' start?",
    "answer": "January"
  },
  {
    "question": "In which now-defunct tournament were competitions held for the MOBA game Heroes of the Storm?",
    "answer": "HGC"
  },
  {
    "question": "Name the magical art of elven mages in the game Dragon Age.",
    "answer": "Arcanum"
  },
  {
    "question": "On which channel are kitchen gadget reviews regularly released?",
    "answer": "Reviews and Gadgets"
  },
  {
    "question": "The character leading the 'Masquerade' clans in Bloodlines is...",
    "answer": "Prince"
  },
  {
    "question": "What allows you to add unique abilities to characters?",
    "answer": "Skill cards"
  },
  {
    "question": "What are Pokémon catchers called in Pokémon GO?",
    "answer": "Trainers"
  },
  {
    "question": "What are intensive tests for games called?",
    "answer": "Stress tests"
  },
  {
    "question": "What are the main resources in the game Hay Day?",
    "answer": "Crops"
  },
  {
    "question": "What are the pieces in Mahjong called?",
    "answer": "Tiles"
  },
  {
    "question": "What are the regular meetings in the game called?",
    "answer": "Events"
  },
  {
    "question": "What can a podcast contain?",
    "answer": "Opinions"
  },
  {
    "question": "What cards are used for healing in the original games?",
    "answer": "Potion cards"
  },
  {
    "question": "What creature helps in the game Monument Valley 2?",
    "answer": "Crow"
  },
  {
    "question": "What creature is encountered in the game 'Gloomhaven'?",
    "answer": "Monster"
  },
  {
    "question": "What does RSS mean?",
    "answer": "Format for publishing news"
  },
  {
    "question": "What does the term 4X mean in strategy games?",
    "answer": "Explore, expand, exploit, exterminate"
  },
  {
    "question": "What does the word 'Tangram' mean?",
    "answer": "Seven boards of skill"
  },
  {
    "question": "What engine does the game DOOM 2016 use?",
    "answer": "id Tech 6"
  },
  {
    "question": "What engine was used to develop the game Grand Theft Auto V?",
    "answer": "RAGE"
  },
  {
    "question": "What event marked the beginning of the Witcher world?",
    "answer": "Conjunction of the Spheres"
  },
  {
    "question": "What game engine is used in The Elder Scrolls V: Skyrim?",
    "answer": "Creation Engine"
  },
  {
    "question": "What genre of VR games is suitable for fitness?",
    "answer": "Rhythm game"
  },
  {
    "question": "What genre of game is considered a team strategy?",
    "answer": "MOBA"
  },
  {
    "question": "What is Motion Capture?",
    "answer": "motion capture"
  },
  {
    "question": "What is a GDD?",
    "answer": "Design document"
  },
  {
    "question": "What is a LAN party?",
    "answer": "Gaming session"
  },
  {
    "question": "What is a gathering of gamers called?",
    "answer": "LAN party"
  },
  {
    "question": "What is a key aspect of an RPG?",
    "answer": "Role-playing"
  },
  {
    "question": "What is an API?",
    "answer": "Application Interface"
  },
  {
    "question": "What is the ability called that characters can use in the game The Elder Scrolls V: Skyrim?",
    "answer": "Dragonborn"
  },
  {
    "question": "What is the attack value of Tarnuhar in the game Gwent?",
    "answer": "10"
  },
  {
    "question": "What is the creation of content for games called?",
    "answer": "Modding"
  },
  {
    "question": "What is the document with the game description called?",
    "answer": "Design document"
  },
  {
    "question": "What is the gameplay of the game Braid based on?",
    "answer": "Time travel"
  },
  {
    "question": "What is the genre of the game Dark Souls?",
    "answer": "Role-playing"
  },
  {
    "question": "What is the genre of the game Dead Cells?",
    "answer": "Roguelike"
  },
  {
    "question": "What is the genre of the game Persona 5?",
    "answer": "JRPG"
  },
  {
    "question": "What is the goal of the 'Iron Maiden' puzzle?",
    "answer": "Open"
  },
  {
    "question": "What is the homeland of the Khuzaits in Mount & Blade?",
    "answer": "Khuzait"
  },
  {
    "question": "What is the in-game chat called?",
    "answer": "Communicator"
  },
  {
    "question": "What is the largest esports organization?",
    "answer": "ESL"
  },
  {
    "question": "What is the largest island in the world?",
    "answer": "Greenland"
  },
  {
    "question": "What is the main objective in the game Monument Valley?",
    "answer": "Solving puzzles"
  },
  {
    "question": "What is the main tournament held for the game StarCraft II?",
    "answer": "WCS"
  },
  {
    "question": "What is the main weapon of Trevor in the game GTA V?",
    "answer": "Shotgun"
  },
  {
    "question": "What is the mode called in Assassin's Creed IV where you can control a ship?",
    "answer": "Naval Battles"
  },
  {
    "question": "What is the most prestigious Hearthstone tournament?",
    "answer": "World Championship"
  },
  {
    "question": "What is the name of a common game server?",
    "answer": "Shard"
  },
  {
    "question": "What is the name of a major gaming event?",
    "answer": "Tournament"
  },
  {
    "question": "What is the name of the Chinese logic game consisting of wooden or plastic sticks that need to be woven in the correct order?",
    "answer": "Mikado"
  },
  {
    "question": "What is the name of the StarCraft tournament?",
    "answer": "GSL"
  },
  {
    "question": "What is the name of the VR game that uses a virtual glove set?",
    "answer": "Hand Simulator"
  },
  {
    "question": "What is the name of the VR game where players can explore the world using a portal gun?",
    "answer": "Portal Stories: VR"
  },
  {
    "question": "What is the name of the ancient Chinese game with black and white stones?",
    "answer": "Go"
  },
  {
    "question": "What is the name of the anti-gravity racing game by Sony?",
    "answer": "Wipeout"
  },
  {
    "question": "What is the name of the author of the channel 'Piano Secrets'?",
    "answer": "Eldar Kasimov"
  },
  {
    "question": "What is the name of the board game where players grow vegetables?",
    "answer": "Agricola"
  },
  {
    "question": "What is the name of the board game with paths and cards?",
    "answer": "The Quest for El Dorado"
  },
  {
    "question": "What is the name of the burgundy puzzle from the 'Professor Stein' series?",
    "answer": "Sphinx"
  },
  {
    "question": "What is the name of the card-based board game where players compete for the best kingdom?",
    "answer": "Dominion"
  },
  {
    "question": "What is the name of the city governed by the Eternal Guardian in the game Divinity: Original Sin?",
    "answer": "Cyclopean"
  },
  {
    "question": "What is the name of the creator of The Elder Scrolls series?",
    "answer": "Todd Howard"
  },
  {
    "question": "What is the name of the creator of the podcast 'Serial'?",
    "answer": "Sarah Koenig"
  },
  {
    "question": "What is the name of the database with details of RPG worlds?",
    "answer": "Omniopedia"
  },
  {
    "question": "What is the name of the enemy in Dead Space?",
    "answer": "Necromorphs"
  },
  {
    "question": "What is the name of the esports player known as 'F0rest'?",
    "answer": "Patrik Lindberg"
  },
  {
    "question": "What is the name of the evil race in the game 'Mass Effect'?",
    "answer": "Reapers"
  },
  {
    "question": "What is the name of the expansion in Pokémon TCG?",
    "answer": "Sword & Shield"
  },
  {
    "question": "What is the name of the famous puzzle creator?",
    "answer": "Martin Gardner"
  },
  {
    "question": "What is the name of the fictional continent in the game Dark Souls?",
    "answer": "Lordran"
  },
  {
    "question": "What is the name of the fictional mirror in the game Mirror's Edge?",
    "answer": "Catalyst"
  },
  {
    "question": "What is the name of the first JRPG?",
    "answer": "Dragon Quest"
  },
  {
    "question": "What is the name of the first classic arcade game?",
    "answer": "Space Invaders"
  },
  {
    "question": "What is the name of the first game about hunting dinosaurs and robots?",
    "answer": "Horizon Zero Dawn"
  },
  {
    "question": "What is the name of the first game by FromSoftware?",
    "answer": "King's Field"
  },
  {
    "question": "What is the name of the first game created by Hideo Kojima?",
    "answer": "Metal Gear"
  },
  {
    "question": "What is the name of the flight simulator by Laminar Research?",
    "answer": "X-Plane"
  },
  {
    "question": "What is the name of the founder of FaZe Clan?",
    "answer": "Thomas Oliveira"
  },
  {
    "question": "What is the name of the game about catching criminals in the Wild West?",
    "answer": "West of Loathing"
  },
  {
    "question": "What is the name of the game about fighting alien invaders on Earth?",
    "answer": "Xenoblade Chronicles"
  },
  {
    "question": "What is the name of the game about managing a city-state in the ancient world?",
    "answer": "Caesar"
  },
  {
    "question": "What is the name of the game based on the comic about punishing evil?",
    "answer": "The Punisher"
  },
  {
    "question": "What is the name of the game based on the concept of an endless dungeon?",
    "answer": "Rogue Legacy"
  },
  {
    "question": "What is the name of the game created by Red Hook Studios?",
    "answer": "Darkest Dungeon"
  },
  {
    "question": "What is the name of the game dedicated to lighting and shadows?",
    "answer": "Noir"
  },
  {
    "question": "What is the name of the game series about the ancient Russian world?",
    "answer": "Knyaz"
  },
  {
    "question": "What is the name of the game where characters are on a floating planet?",
    "answer": "Gravity Ghost"
  },
  {
    "question": "What is the name of the game where players become detectives?",
    "answer": "Sherlock Holmes: Consulting Detective"
  },
  {
    "question": "What is the name of the game where players explore a maze?",
    "answer": "Labyrinth"
  },
  {
    "question": "What is the name of the game where survival is critically important?",
    "answer": "Survival Craft"
  },
  {
    "question": "What is the name of the game where the main action takes place during the Japanese invasion of Tsushima Island?",
    "answer": "Ghost of Tsushima"
  },
  {
    "question": "What is the name of the game where you can control a spaceship?",
    "answer": "FTL: Faster Than Light"
  },
  {
    "question": "What is the name of the game where you can develop in a post-apocalyptic world?",
    "answer": "Fallout Shelter"
  },
  {
    "question": "What is the name of the game where you can manage a space station?",
    "answer": "Space Station 13"
  },
  {
    "question": "What is the name of the game where you capture a castle?",
    "answer": "Castle Crashers"
  },
  {
    "question": "What is the name of the game where you need to develop a charter agency?",
    "answer": "Airline Tycoon"
  },
  {
    "question": "What is the name of the game where you need to line up rows of identical tiles?",
    "answer": "Bejeweled"
  },
  {
    "question": "What is the name of the game where you need to solve puzzles with mechanical objects?",
    "answer": "The Room"
  },
  {
    "question": "What is the name of the game with survival mechanics on an island?",
    "answer": "Stranded Deep"
  },
  {
    "question": "What is the name of the hunting simulator?",
    "answer": "theHunter"
  },
  {
    "question": "What is the name of the indie game where you need to find light crystals?",
    "answer": "Hyper Light Drifter"
  },
  {
    "question": "What is the name of the island where the game Rime takes place?",
    "answer": "Tlamac"
  },
  {
    "question": "What is the name of the location where most of the action in the game 'BioShock' takes place?",
    "answer": "Rapture"
  },
  {
    "question": "What is the name of the logic game where you need to connect dots with lines, avoiding intersections?",
    "answer": "Pontoon"
  },
  {
    "question": "What is the name of the magical crystal in the game Kingdom Hearts?",
    "answer": "Crystal of Light"
  },
  {
    "question": "What is the name of the main antagonist in the Resident Evil game series?",
    "answer": "Albert Wesker"
  },
  {
    "question": "What is the name of the main antagonist in the game 'Silent Hill 2'?",
    "answer": "Pyramid Head"
  },
  {
    "question": "What is the name of the main antagonist in the game Shovel Knight?",
    "answer": "The Enchantress"
  },
  {
    "question": "What is the name of the main character in the 'Resident Evil' game series?",
    "answer": "Leon Kennedy"
  },
  {
    "question": "What is the name of the main character in the game Bloodborne?",
    "answer": "Hunter"
  },
  {
    "question": "What is the name of the main character in the game Horizon Zero Dawn?",
    "answer": "Aloy"
  },
  {
    "question": "What is the name of the main character in the game Saints Row IV?",
    "answer": "The President"
  },
  {
    "question": "What is the name of the main character in the game Sekiro: Shadows Die Twice?",
    "answer": "Wolf"
  },
  {
    "question": "What is the name of the main character's weapon in the game Doom 2016?",
    "answer": "BFG 9000"
  },
  {
    "question": "What is the name of the major tournament for the game Overwatch?",
    "answer": "Overwatch League"
  },
  {
    "question": "What is the name of the mask that Kratos is searching for in the game God of War: Ragnarok?",
    "answer": "Mask of the Ancients"
  },
  {
    "question": "What is the name of the mobile game with survival elements?",
    "answer": "Terraria"
  },
  {
    "question": "What is the name of the mobile life simulation game?",
    "answer": "BitLife"
  },
  {
    "question": "What is the name of the mysterious puzzle game by Capybara Games?",
    "answer": "Super Time Force"
  },
  {
    "question": "What is the name of the online conference for gamers?",
    "answer": "Convention"
  },
  {
    "question": "What is the name of the open-world game by Ubisoft released in 2020?",
    "answer": "Assassin's Creed Valhalla"
  },
  {
    "question": "What is the name of the open-world game with resource gathering in survival mode?",
    "answer": "Rust"
  },
  {
    "question": "What is the name of the people's assembly in 'Final Fantasy X'?",
    "answer": "Highbridge"
  },
  {
    "question": "What is the name of the popular music streamer who often plays the guitar?",
    "answer": "Sungha Jung"
  },
  {
    "question": "What is the name of the popular space game?",
    "answer": "EVE Online"
  },
  {
    "question": "What is the name of the post-apocalyptic role-playing game developed by InXile Entertainment?",
    "answer": "Wasteland 3"
  },
  {
    "question": "What is the name of the program used for creating textures?",
    "answer": "Substance Painter"
  },
  {
    "question": "What is the name of the puzzle that uses a chessboard?",
    "answer": "Studies"
  },
  {
    "question": "What is the name of the puzzle with spirals?",
    "answer": "Spirogram"
  },
  {
    "question": "What is the name of the racing track simulator game?",
    "answer": "Assetto Corsa"
  },
  {
    "question": "What is the name of the railway simulator by Dovetail Games?",
    "answer": "Train Simulator"
  },
  {
    "question": "What is the name of the science fiction game created by the FreeSpace team?",
    "answer": "FreeSpace 2"
  },
  {
    "question": "What is the name of the small town in the game Oxenfree?",
    "answer": "Camena"
  },
  {
    "question": "What is the name of the space battle simulation game?",
    "answer": "EVE Online"
  },
  {
    "question": "What is the name of the survival simulator with dinosaurs?",
    "answer": "ARK: Survival Evolved"
  },
  {
    "question": "What is the name of the sword in The Legend of Zelda?",
    "answer": "Master Sword"
  },
  {
    "question": "What is the name of the virtual fitness club in VR?",
    "answer": "FitXR"
  },
  {
    "question": "What is the name of the world in the game Subnautica?",
    "answer": "4546B"
  },
  {
    "question": "What is the objective of the game 'Jumanji'?",
    "answer": "Finish the game"
  },
  {
    "question": "What is the process of creating and synchronizing the movements of characters and objects called?",
    "answer": "Animation"
  },
  {
    "question": "What is the process of forming a deck called?",
    "answer": "Draft"
  },
  {
    "question": "What is the real name of the esports player known as 'GeT_RiGhT'?",
    "answer": "Christopher Alesund"
  },
  {
    "question": "What is the system called for automatic game code quality checking?",
    "answer": "CI"
  },
  {
    "question": "What is the technology of creating graphics using dots called?",
    "answer": "Raster graphics"
  },
  {
    "question": "What is the term for a serious breakdown in a game?",
    "answer": "Tilt"
  },
  {
    "question": "What is the term for an irreversible loss in a game?",
    "answer": "Wasted"
  },
  {
    "question": "What is the term for improving game mechanics?",
    "answer": "Update"
  },
  {
    "question": "What is the term for reducing the number of cards in a deck?",
    "answer": "Minus deck"
  },
  {
    "question": "What is the ultimate goal set for players in the game 'No Man's Sky'?",
    "answer": "Center of the galaxy"
  },
  {
    "question": "What is the visual layer of a game interface called?",
    "answer": "HUD"
  },
  {
    "question": "What is the world in The Elder Scrolls called?",
    "answer": "Nirn"
  },
  {
    "question": "What prize is often awarded at LoL tournaments?",
    "answer": "Skin Pack"
  },
  {
    "question": "What programming language is the Godot engine written in?",
    "answer": "C++"
  },
  {
    "question": "What puzzles use mathematical operations?",
    "answer": "Mathematical puzzles"
  },
  {
    "question": "What resource is needed to change characters?",
    "answer": "Growth Cards"
  },
  {
    "question": "What role does the main character play in the game Hellblade: Senua's Sacrifice?",
    "answer": "Warrior"
  },
  {
    "question": "What tournament is held for Blizzard games in the middle of the year?",
    "answer": "Midseason Madness"
  },
  {
    "question": "What tournament is held for the game Clash Royale?",
    "answer": "CRL"
  },
  {
    "question": "What tournament is held for the game Fortnite?",
    "answer": "FNCS"
  },
  {
    "question": "What tournament is held for the game Street Fighter?",
    "answer": "Capcom Cup"
  },
  {
    "question": "What type of cards allows players to cast spells in Magic: The Gathering?",
    "answer": "Instants"
  },
  {
    "question": "What type of cards are used to create combinations in Yu-Gi-Oh!?",
    "answer": "Synchro"
  },
  {
    "question": "What type of deck is used in the 'Commander' mode in MTG?",
    "answer": "100 cards"
  },
  {
    "question": "What type of game is 'Carcassonne'?",
    "answer": "Strategy"
  },
  {
    "question": "What type of magic cards exist in Yu-Gi-Oh!?",
    "answer": "Field"
  },
  {
    "question": "What type of puzzle involves the analysis of biomorphs?",
    "answer": "Biomorphology"
  },
  {
    "question": "What type of puzzle is a magic square?",
    "answer": "Magic square"
  },
  {
    "question": "What type of puzzles includes pieces that move?",
    "answer": "Sliding puzzles"
  },
  {
    "question": "What unique ability does the 'Worgen' class have in World of Warcraft?",
    "answer": "Transformation"
  },
  {
    "question": "What was the first MMORPG?",
    "answer": "Meridian 59"
  },
  {
    "question": "What was the first mass-produced interactive video game?",
    "answer": "Spacewar!"
  },
  {
    "question": "What was the name of the first Battle Royale game?",
    "answer": "H1Z1"
  },
  {
    "question": "When was the first Mario game released?",
    "answer": "1981"
  },
  {
    "question": "Where does the game Baldur's Gate take place?",
    "answer": "Faerûn"
  },
  {
    "question": "Where does the game The Witcher 3 begin?",
    "answer": "Vizima"
  },
  {
    "question": "Where is The International tournament usually held?",
    "answer": "USA"
  },
  {
    "question": "Where is the EVO tournament held?",
    "answer": "Las Vegas"
  },
  {
    "question": "Which AR game allows you to draw in the real world?",
    "answer": "Just a Line"
  },
  {
    "question": "Which AR game involves creating fantasy worlds?",
    "answer": "Harry Potter: Wizards Unite"
  },
  {
    "question": "Which AR game promotes nature exploration?",
    "answer": "Jurassic World Alive"
  },
  {
    "question": "Which Apex Legends tournament is considered the most prestigious?",
    "answer": "ALGS Championship"
  },
  {
    "question": "Which MTG set first introduced double-faced cards?",
    "answer": "Innistrad"
  },
  {
    "question": "Which Magic: The Gathering card is considered the most expensive?",
    "answer": "Black Lotus"
  },
  {
    "question": "Which Magic: The Gathering format allows the use of cards from all sets?",
    "answer": "Vintage"
  },
  {
    "question": "Which StarCraft II tournament is considered the most prestigious?",
    "answer": "WCS Global Finals"
  },
  {
    "question": "Which VR game allows players to explore the world using a portal gun?",
    "answer": "Half-Life: Alyx"
  },
  {
    "question": "Which VR game allows you to command a virtual fleet?",
    "answer": "Star Trek: Bridge Crew"
  },
  {
    "question": "Which VR game allows you to control the movements of a pirate ship?",
    "answer": "Sea of Pirates"
  },
  {
    "question": "Which VR game allows you to participate in space battles?",
    "answer": "Galaxy War"
  },
  {
    "question": "Which VR game allows you to play musical instruments?",
    "answer": "Electronauts"
  },
  {
    "question": "Which VR game is associated with programming robots?",
    "answer": "Human Resource Machine"
  },
  {
    "question": "Which VR game is known for its thrilling tank battles?",
    "answer": "World of Tanks VR"
  },
  {
    "question": "Which VR game is related to the life of an ant?",
    "answer": "Ant Simulator"
  },
  {
    "question": "Which VR game simulates a robot war?",
    "answer": "Mech Battle"
  },
  {
    "question": "Which Yu-Gi-Oh! set introduced the 'Destiny Hero' series of cards?",
    "answer": "Destiny Soldiers"
  },
  {
    "question": "Which animal is present in the game 'Carcassonne'?",
    "answer": "Dragon"
  },
  {
    "question": "Which artist combines live performance with DJ sets?",
    "answer": "Kaskade"
  },
  {
    "question": "Which audience prefers podcasts?",
    "answer": "Adults"
  },
  {
    "question": "Which blogger is involved in creating makeup and wigs for shows?",
    "answer": "Miss Fame"
  },
  {
    "question": "Which blogger is known for promoting CrossFit?",
    "answer": "Ilya Zakharov"
  },
  {
    "question": "Which blogger is known for their high professionalism in makeup?",
    "answer": "Wei Li"
  },
  {
    "question": "Which blogger is known for their philosophical reflections?",
    "answer": "Frolov"
  },
  {
    "question": "Which blogger often uses bright color schemes in makeup?",
    "answer": "Patrick Starrr"
  },
  {
    "question": "Which blogger shares knowledge about history?",
    "answer": "Andrey Ilyin"
  },
  {
    "question": "Which blogger specializes in makeup for horror movies?",
    "answer": "Glam Gore"
  },
  {
    "question": "Which blogger specializes in retro looks?",
    "answer": "Stephanie Lan"
  },
  {
    "question": "Which board game involves moving pieces on a hexagonal board with goals of economy and diplomacy?",
    "answer": "Terra Mystica"
  },
  {
    "question": "Which board game is dedicated to in-depth exploration and excavation?",
    "answer": "Archaeologists"
  },
  {
    "question": "Which board game ranks third in popularity worldwide?",
    "answer": "Risk"
  },
  {
    "question": "Which boss is an enemy in the game Bloodborne?",
    "answer": "Laurence"
  },
  {
    "question": "Which channel debunks kitchen myths?",
    "answer": "Myths and Kitchen"
  },
  {
    "question": "Which character appears in the game Monument Valley?",
    "answer": "Ida"
  },
  {
    "question": "Which company organizes the esports tournament CDL?",
    "answer": "Activision"
  },
  {
    "question": "Which company owns Oculus?",
    "answer": "Facebook"
  },
  {
    "question": "Which culinary blogger is known for their videos about fermented products?",
    "answer": "Alexander Khlebnikov"
  },
  {
    "question": "Which dragon is trapped in Skyrim?",
    "answer": "Odahviing"
  },
  {
    "question": "Which element adds enhancements to cards in MTG?",
    "answer": "Artifact"
  },
  {
    "question": "Which esports organization hosts Call of Duty tournaments?",
    "answer": "CDL"
  },
  {
    "question": "Which faction is represented in World of Warcraft?",
    "answer": "Horde"
  },
  {
    "question": "Which female athlete streams about swimming?",
    "answer": "Marina Osipova"
  },
  {
    "question": "Which game allows players to build a city on post-apocalyptic land?",
    "answer": "Surviving the Aftermath"
  },
  {
    "question": "Which game allows players to build and manage a partisan movement?",
    "answer": "Partisans"
  },
  {
    "question": "Which game allows you to develop industry and economy?",
    "answer": "Industries of Titan"
  },
  {
    "question": "Which game allows you to recreate historical battles and scenarios?",
    "answer": "Total War"
  },
  {
    "question": "Which game attracted attention with its storyline in 2018?",
    "answer": "Red Dead Redemption 2"
  },
  {
    "question": "Which game combines elements of a post-apocalyptic world and turn-based combat?",
    "answer": "Wasteland"
  },
  {
    "question": "Which game company created the Xenoblade Chronicles series?",
    "answer": "Monolith Soft"
  },
  {
    "question": "Which game explores an alternate history of battles on the Eastern Front?",
    "answer": "Command & Conquer: Red Alert"
  },
  {
    "question": "Which game has a mode reminiscent of dungeons?",
    "answer": "MTG"
  },
  {
    "question": "Which game in the Dark Souls series lacks a multiplayer mode?",
    "answer": "Demon's Souls"
  },
  {
    "question": "Which game includes VR flights?",
    "answer": "Ultrawings"
  },
  {
    "question": "Which game includes cards with the type 'Ice Lander'?",
    "answer": "Flesh and Blood"
  },
  {
    "question": "Which game introduced the health pack system and health regeneration?",
    "answer": "Wolfenstein 3D"
  },
  {
    "question": "Which game involves missions to explore technology and survive in arctic climate conditions?",
    "answer": "Frostpunk"
  },
  {
    "question": "Which game is a spin-off of the Persona series?",
    "answer": "Persona Q"
  },
  {
    "question": "Which game is about a glitch-computer and the pursuit of criminals?",
    "answer": "Hacknet"
  },
  {
    "question": "Which game is based on myths and legends?",
    "answer": "Myth"
  },
  {
    "question": "Which game is dedicated to traveling through post-apocalyptic London?",
    "answer": "Dying Light"
  },
  {
    "question": "Which game is known for its high level of difficulty?",
    "answer": "Dark Souls"
  },
  {
    "question": "Which game is known for its historical campaigns?",
    "answer": "Europa Universalis"
  },
  {
    "question": "Which game is known for its release in 2020?",
    "answer": "Cyberpunk 2077"
  },
  {
    "question": "Which game is known for its serious storylines?",
    "answer": "The Last of Us"
  },
  {
    "question": "Which game is known for its sword fights and intense battles?",
    "answer": "Dark Souls"
  },
  {
    "question": "Which game is known for the mythic card 'Black Lotus'?",
    "answer": "Magic: The Gathering"
  },
  {
    "question": "Which game is over 1500 years old?",
    "answer": "Chess"
  },
  {
    "question": "Which game is popular among Japanese people due to its many combinations?",
    "answer": "Go"
  },
  {
    "question": "Which game is popular due to augmented reality technology?",
    "answer": "Ingress"
  },
  {
    "question": "Which game is popular for its dark atmosphere?",
    "answer": "Bloodborne"
  },
  {
    "question": "Which game is set in post-apocalyptic Siberia?",
    "answer": "Metro Exodus"
  },
  {
    "question": "Which game offers players the chance to manage a city in a post-apocalyptic world?",
    "answer": "Frostpunk"
  },
  {
    "question": "Which game offers the creation and management of a partisan movement?",
    "answer": "Partisans 1941"
  },
  {
    "question": "Which game series is known for its difficulty and rolling mechanics?",
    "answer": "Dark Souls"
  },
  {
    "question": "Which game takes place in a world of flights and skies?",
    "answer": "Sky: Children of the Light"
  },
  {
    "question": "Which game was based on the popular Adult Swim animated series?",
    "answer": "Rick and Morty: Pocket Mortys"
  },
  {
    "question": "Which game was the first to introduce an achievement system?",
    "answer": "Halo 3"
  },
  {
    "question": "Which game was the first to use polygonal graphics?",
    "answer": "Battlezone"
  },
  {
    "question": "Which game was the original source for the 'Far Cry' game series?",
    "answer": "Far Cry"
  },
  {
    "question": "Which gaming console was the first 16-bit console?",
    "answer": "Sega Genesis"
  },
  {
    "question": "Which genre is not suitable for educational podcasts?",
    "answer": "Thriller"
  },
  {
    "question": "Which graphics library is used in Vulkan?",
    "answer": "Vulkan API"
  },
  {
    "question": "Which horror game tells the story of an island taken over by maniacs?",
    "answer": "The Forest"
  },
  {
    "question": "Which indie game explores the theme of life and death?",
    "answer": "Spiritfarer"
  },
  {
    "question": "Which indie game is a mix of strategy and puzzles?",
    "answer": "Papers, Please"
  },
  {
    "question": "Which indie game is about adventures in 1920s Spain?",
    "answer": "Blasphemous"
  },
  {
    "question": "Which indie game tells the story of life on a space station?",
    "answer": "Tacoma"
  },
  {
    "question": "Which mathematical puzzle is the competition dedicated to?",
    "answer": "Sudoku"
  },
  {
    "question": "Which modern game is based on the ancient Chinese game 'Mahjong'?",
    "answer": "Mahjong"
  },
  {
    "question": "Which organization hosts the DreamHack tournament?",
    "answer": "DreamHack AB"
  },
  {
    "question": "Which podcast discusses investments?",
    "answer": "Investment Club"
  },
  {
    "question": "Which podcast mixes music and humor?",
    "answer": "Musicomedy"
  },
  {
    "question": "Which podcast often combines humor and politics?",
    "answer": "Politically Joking"
  },
  {
    "question": "Which podcast teaches investing?",
    "answer": "Investing for Everyone"
  },
  {
    "question": "Which puzzle can be solved by moving rings?",
    "answer": "Tower of Hanoi"
  },
  {
    "question": "Which puzzle is a fusion of even prints?",
    "answer": "Kotorika"
  },
  {
    "question": "Which puzzle requires assembling a three-dimensional figure from connected cubes?",
    "answer": "Soma Cube"
  },
  {
    "question": "Which role-playing online game is known for its large tournaments?",
    "answer": "World of Warcraft"
  },
  {
    "question": "Which simulator allows you to become a magazine editor?",
    "answer": "Magazine Mogul"
  },
  {
    "question": "Which simulator allows you to manage a gas station?",
    "answer": "Gas Station Simulator"
  },
  {
    "question": "Which simulator allows you to manage an aquarium?",
    "answer": "Megaquarium"
  },
  {
    "question": "Which simulator is dedicated to post-apocalyptic survival?",
    "answer": "Project Zomboid"
  },
  {
    "question": "Which skill is responsible for the art of persuasion?",
    "answer": "Speech"
  },
  {
    "question": "Which streamer goes by the pseudonym Dr Disrespect?",
    "answer": "Guy Beahm"
  },
  {
    "question": "Which streamer performs their own songs in hip-hop style?",
    "answer": "Watsky"
  },
  {
    "question": "Which streamer regularly performs piano covers?",
    "answer": "CassyJam"
  },
  {
    "question": "Which studio developed the game The Last Guardian?",
    "answer": "Team Ico"
  },
  {
    "question": "Which team does the esports player Puppey play for?",
    "answer": "Team Secret"
  },
  {
    "question": "Which team won the 2020 League of Legends World Championship?",
    "answer": "DAMWON Gaming"
  },
  {
    "question": "Which team won the LEC 2020 tournament in LoL?",
    "answer": "G2 Esports"
  },
  {
    "question": "Which team won the PGL Major Stockholm 2021 in CS:GO?",
    "answer": "NAVI"
  },
  {
    "question": "Which tournament is held in South Korea for real-time strategy games?",
    "answer": "GSL"
  },
  {
    "question": "Which video game was the first to receive an ESRB rating?",
    "answer": "Mortal Kombat"
  },
  {
    "question": "Which virtual reality game allows players to explore dungeons?",
    "answer": "The Mage's Tale"
  },
  {
    "question": "Who controls the game session?",
    "answer": "Admin"
  },
  {
    "question": "Who created Metal Gear Solid?",
    "answer": "Hideo Kojima"
  },
  {
    "question": "Who developed the game 'Path of Exile'?",
    "answer": "Grinding Gear Games"
  },
  {
    "question": "Who founded the company Team Liquid?",
    "answer": "Victor Goossens"
  },
  {
    "question": "Who founded the organization Cloud9?",
    "answer": "Jack Etienne"
  },
  {
    "question": "Who hosts the podcast \"Cultural Focus\"?",
    "answer": "Anna Petrova"
  },
  {
    "question": "Who is considered the founder of the RPG genre?",
    "answer": "Gary Gygax"
  },
  {
    "question": "Who is known for their retro looks?",
    "answer": "Lucia Vander"
  },
  {
    "question": "Who is responsible for setting up lighting in a game?",
    "answer": "Technical artist"
  },
  {
    "question": "Who is the author of the 'sand eyes' concept?",
    "answer": "Tati Westbrook"
  },
  {
    "question": "Who is the creator of LiveJournal?",
    "answer": "Brad Fitzpatrick"
  },
  {
    "question": "Who is the creator of the character Mario?",
    "answer": "Shigeru Miyamoto"
  },
  {
    "question": "Who is the head of the guild?",
    "answer": "Leader"
  },
  {
    "question": "Who is the lead designer of the game 'The Sims'?",
    "answer": "Will Wright"
  },
  {
    "question": "Who is the main antagonist in the Half-Life game series?",
    "answer": "Nihilanth"
  },
  {
    "question": "Who is the main antagonist in the game Hyper Light Drifter?",
    "answer": "Titans"
  },
  {
    "question": "Who is the main antagonist in the game Shadow of the Colossus?",
    "answer": "Dormin"
  },
  {
    "question": "Who is the main antagonist of Sam Porter in the game Death Stranding?",
    "answer": "Higgs"
  },
  {
    "question": "Who is the main enemy in the game Bloodborne?",
    "answer": "Beasts"
  },
  {
    "question": "Who is the main protagonist in the Fallout game series?",
    "answer": "The Lone Wanderer"
  },
  {
    "question": "Who is the main protagonist of the Assassin's Creed game series?",
    "answer": "Desmond Miles"
  },
  {
    "question": "Who is the most decorated player in the EVO Tekken tournament?",
    "answer": "Qudans"
  },
  {
    "question": "Who is the organizer of the Blast Premier CS:GO tournament?",
    "answer": "RFRSH Entertainment"
  },
  {
    "question": "Who programs the logical interactions in a game?",
    "answer": "Gameplay programmer"
  },
  {
    "question": "Who shares knowledge about biology?",
    "answer": "Maria Kuzmina"
  },
  {
    "question": "Who talks about psychology on their YouTube channel?",
    "answer": "Dmitry Panov"
  },
  {
    "question": "Who talks about space and astronomy?",
    "answer": "Oleg Vasilyev"
  },
  {
    "question": "Who was the commentator at The Overwatch League tournament?",
    "answer": "MonteCristo"
  },
  {
    "question": "Who won the 2023 World Chess Championship?",
    "answer": "Ding Liren"
  },
  {
    "question": "Who won the DreamHack Masters 2021 CS:GO tournament?",
    "answer": "Gambit Esports"
  },
  {
    "question": "Who won the EVO 2021 tournament for Street Fighter V?",
    "answer": "iDom"
  },
  {
    "question": "Who won the Free Fire World Series 2021 tournament?",
    "answer": "Phoenix Force"
  },
  {
    "question": "Who won the IEM Katowice 2020 tournament in StarCraft II?",
    "answer": "Rogue"
  },
  {
    "question": "Who won the MLG 2007 tournament for Halo 2?",
    "answer": "Final Boss"
  },
  {
    "question": "Who won the MPL tournament in 2020?",
    "answer": "Bren Esports"
  },
  {
    "question": "Who won the PMCO Spring Split 2021 tournament in PUBG Mobile?",
    "answer": "Fanatic Zombies"
  },
  {
    "question": "Who won the PUBG Global Championship 2019?",
    "answer": "Gen.G"
  },
  {
    "question": "Who won the Teamfight Tactics World Championship in 2021?",
    "answer": "3Zz"
  }
]